selenium_stealth_helper/__init__.py
selenium_stealth_helper/cloudflare_tools.py
selenium_stealth_helper/stealth_helper.py
selenium_stealth_helper/webdriver_utils.py
selenium_stealth_helper-1.1.4.dist-info/licenses/LICENSE
selenium_stealth_helper-1.1.4.dist-info/METADATA
selenium_stealth_helper-1.1.4.dist-info/WHEEL
selenium_stealth_helper-1.1.4.dist-info/top_level.txt
selenium_stealth_helper-1.1.4.dist-info/RECORD
