Metadata-Version: 2.4
Name: selenium-stealth-helper
Version: 1.1.4
Summary: Enhanced Selenium stealth automation tools with Cloudflare bypass capabilities
Home-page: https://github.com/web-automation/selenium-stealth-helper
Author: Web Automation Team
Author-email: Web Automation Team <web.automation@example.com>
Maintainer-email: Web Automation Team <web.automation@example.com>
License: MIT
Project-URL: Homepage, https://github.com/web-automation/selenium-stealth-helper
Project-URL: Documentation, https://github.com/web-automation/selenium-stealth-helper#readme
Project-URL: Repository, https://github.com/web-automation/selenium-stealth-helper
Project-URL: Bug Tracker, https://github.com/web-automation/selenium-stealth-helper/issues
Keywords: selenium,stealth,automation,cloudflare,bypass,webdriver
Classifier: Development Status :: 4 - Beta
Classifier: Intended Audience :: Developers
Classifier: License :: OSI Approved :: MIT License
Classifier: Operating System :: OS Independent
Classifier: Programming Language :: Python :: 3
Classifier: Programming Language :: Python :: 3.7
Classifier: Programming Language :: Python :: 3.8
Classifier: Programming Language :: Python :: 3.9
Classifier: Programming Language :: Python :: 3.10
Classifier: Programming Language :: Python :: 3.11
Classifier: Topic :: Software Development :: Libraries :: Python Modules
Classifier: Topic :: Internet :: WWW/HTTP :: Browsers
Classifier: Topic :: Security
Requires-Python: >=3.7
License-File: LICENSE
Requires-Dist: selenium>=4.0.0
Requires-Dist: selenium-stealth>=1.0.0
Requires-Dist: requests>=2.25.0
Requires-Dist: colorama>=0.4.4
Requires-Dist: beautifulsoup4>=4.9.0
Requires-Dist: psutil>=5.8.0
Provides-Extra: dev
Requires-Dist: pytest>=6.0; extra == "dev"
Requires-Dist: pytest-cov>=2.0; extra == "dev"
Requires-Dist: black>=21.0; extra == "dev"
Requires-Dist: flake8>=3.8; extra == "dev"
Dynamic: author
Dynamic: home-page
Dynamic: license-file
Dynamic: requires-python
